<annotation>
	<folder>JPEGImages</folder>
	<filename>Misc_408.png</filename>
	<path>E:\code\sirst_data\VOC2007\JPEGImages\Misc_408.png</path>
	<source>
		<database>Unknown</database>
	</source>
	<size>
		<width>310</width>
		<height>310</height>
		<depth>3</depth>
	</size>
	<segmented>0</segmented>
	<object>
		<name>Target</name>
		<pose>Unspecified</pose>
		<truncated>0</truncated>
		<difficult>0</difficult>
		<bndbox>
			<xmin>142</xmin>
			<ymin>32</ymin>
			<xmax>154</xmax>
			<ymax>40</ymax>
		</bndbox>
	</object>
</annotation>
