<annotation>
	<folder>JPEGImages</folder>
	<filename>Misc_417.png</filename>
	<path>E:\code\sirst_data\VOC2007\JPEGImages\Misc_417.png</path>
	<source>
		<database>Unknown</database>
	</source>
	<size>
		<width>335</width>
		<height>220</height>
		<depth>3</depth>
	</size>
	<segmented>0</segmented>
	<object>
		<name>Target</name>
		<pose>Unspecified</pose>
		<truncated>0</truncated>
		<difficult>0</difficult>
		<bndbox>
			<xmin>153</xmin>
			<ymin>13</ymin>
			<xmax>158</xmax>
			<ymax>18</ymax>
		</bndbox>
	</object>
</annotation>
